roam/__init__.py
roam/runner.py
roam_python-1.1.2.dist-info/METADATA
roam_python-1.1.2.dist-info/WHEEL
roam_python-1.1.2.dist-info/top_level.txt
roam_python-1.1.2.dist-info/RECORD
