Metadata-Version: 2.1
Name: roam-python
Version: 1.1.2
Summary: Roam python SDK to listen to location updates.
Home-page: UNKNOWN
Author: roam.ai
Author-email: services@roam.ai
License: MIT
Platform: UNKNOWN
Classifier: License :: OSI Approved :: MIT License
Requires-Python: >=3.5
Requires-Dist: paho-mqtt
